piece/__init__.py
piece/digits.py
piece/tree.py
piece/udigit.py
piece/udigits.py
piece/utime.py
piece/utree.py
piece3941-0.0.4.dist-info/LICENSE
piece3941-0.0.4.dist-info/METADATA
piece3941-0.0.4.dist-info/WHEEL
piece3941-0.0.4.dist-info/top_level.txt
piece3941-0.0.4.dist-info/RECORD
