Metadata-Version: 2.1
Name: piece3941
Version: 0.0.4
Summary: Useful Code Piece.
Home-page: https://github.com/RedFoxAtAsleep/piece
Author: redfoxatasleep
Author-email: bbxxone@qq.com
License: UNKNOWN
Platform: UNKNOWN
Classifier: Programming Language :: Python :: 3
Classifier: License :: OSI Approved :: MIT License
Classifier: Operating System :: OS Independent
Requires-Python: >=3.4
